pyrre/__init__.py
pyrre/ferre.py
pyrre/utils.py
pyrre-1.0.0.dist-info/LICENSE
pyrre-1.0.0.dist-info/METADATA
pyrre-1.0.0.dist-info/WHEEL
pyrre-1.0.0.dist-info/top_level.txt
pyrre-1.0.0.dist-info/RECORD
