Metadata-Version: 2.1
Name: pyrre
Version: 1.0.0
Summary: PyRRE: Python code to run the fortran FERRE package to fit synthetic spectra
Home-page: https://github.com/dnidever/pyrre
Author: David Nidever
Author-email: David Nidever <dnidever@montana.edu>
Maintainer-email: David Nidever <dnidever@montana.edu>
License: MIT License
Project-URL: Documentation, https://readthedocs.org
Project-URL: Repository, https://github.com/dnidever/pyrre
Keywords: spectroscopy,abundances
Classifier: Development Status :: 3 - Alpha
Classifier: License :: OSI Approved :: MIT License
Classifier: Programming Language :: Python
Requires: numpy
Requires: astropy(>=4.0)
Requires: scipy
Requires: ferre
Requires-Python: >=3.9
License-File: LICENSE
Requires-Dist: scipy
Requires-Dist: numpy
Requires-Dist: matplotlib
Requires-Dist: astropy
Requires-Dist: dill
Requires-Dist: dlnpyutils
Requires-Dist: ferre
Provides-Extra: cli
Requires-Dist: rich ; extra == 'cli'
Requires-Dist: click ; extra == 'cli'
Provides-Extra: docs
Requires-Dist: sphinx ; extra == 'docs'
Requires-Dist: sphinx-astropy ; extra == 'docs'
Requires-Dist: nbsphinx ; extra == 'docs'
Requires-Dist: nbconvert ; extra == 'docs'
Requires-Dist: nbformat ; extra == 'docs'
Requires-Dist: ipykernel ; extra == 'docs'
Provides-Extra: gui
Requires-Dist: PyQt5 ; extra == 'gui'
Provides-Extra: test
Requires-Dist: pytest ; extra == 'test'
Requires-Dist: pytest-astropy ; extra == 'test'
Requires-Dist: ipython ; extra == 'test'
